term_mark/cmd_parse.py
term_mark/constants.py
term_mark/database.py
term_mark/directory_walk.py
term_mark/main.py
term_mark/menus.py
term_mark/schemas.py
term_mark/tm.zsh
term_mark/tm_functions.py
term_mark/InquirerPy/InquirerPy/__init__.py
term_mark/InquirerPy/InquirerPy/enum.py
term_mark/InquirerPy/InquirerPy/exceptions.py
term_mark/InquirerPy/InquirerPy/inquirer.py
term_mark/InquirerPy/InquirerPy/resolver.py
term_mark/InquirerPy/InquirerPy/separator.py
term_mark/InquirerPy/InquirerPy/utils.py
term_mark/InquirerPy/InquirerPy/validator.py
term_mark/InquirerPy/InquirerPy/base/__init__.py
term_mark/InquirerPy/InquirerPy/base/complex.py
term_mark/InquirerPy/InquirerPy/base/control.py
term_mark/InquirerPy/InquirerPy/base/list.py
term_mark/InquirerPy/InquirerPy/base/simple.py
term_mark/InquirerPy/InquirerPy/containers/__init__.py
term_mark/InquirerPy/InquirerPy/containers/instruction.py
term_mark/InquirerPy/InquirerPy/containers/message.py
term_mark/InquirerPy/InquirerPy/containers/spinner.py
term_mark/InquirerPy/InquirerPy/containers/validation.py
term_mark/InquirerPy/InquirerPy/prompts/__init__.py
term_mark/InquirerPy/InquirerPy/prompts/checkbox.py
term_mark/InquirerPy/InquirerPy/prompts/fuzzy.py
term_mark/InquirerPy/InquirerPy/prompts/list.py
term_mark-0.1.5.dist-info/LICENSE
term_mark-0.1.5.dist-info/METADATA
term_mark-0.1.5.dist-info/WHEEL
term_mark-0.1.5.dist-info/entry_points.txt
term_mark-0.1.5.dist-info/top_level.txt
term_mark-0.1.5.dist-info/RECORD
