Metadata-Version: 2.1
Name: term-mark
Version: 0.1.5
Summary: Bookmarks for your terminal
Author: Andrew Stone
License: Copyright (c) 2023 Andrew Stone
Project-URL: Homepage, https://github.com/exastone/term-mark
Classifier: Programming Language :: Python :: 3
Classifier: License :: OSI Approved :: MIT License
Classifier: Operating System :: OS Independent
Classifier: Topic :: System :: Shells
Classifier: Topic :: Terminals
Classifier: Topic :: Utilities
Requires-Python: >=3.7
License-File: LICENSE
Requires-Dist: pfzy >=0.3.4
Requires-Dist: prompt-toolkit >=3.0.39
